PythonRengongzhinengZhongwenbanChuyi/README.md
PythonRengongzhinengZhongwenbanChuyi/__init__.py
PythonRengongzhinengZhongwenbanChuyi/__main__.py
PythonRengongzhinengZhongwenbanChuyi/file.epub
PythonRengongzhinengZhongwenbanChuyi/index.html
PythonRengongzhinengZhongwenbanChuyi/css/__init__.py
PythonRengongzhinengZhongwenbanChuyi/css/annotations.css
PythonRengongzhinengZhongwenbanChuyi/css/main.css
PythonRengongzhinengZhongwenbanChuyi/css/normalize.css
PythonRengongzhinengZhongwenbanChuyi/css/popup.css
PythonRengongzhinengZhongwenbanChuyi/font/__init__.py
PythonRengongzhinengZhongwenbanChuyi/font/fontello.eot
PythonRengongzhinengZhongwenbanChuyi/font/fontello.svg
PythonRengongzhinengZhongwenbanChuyi/font/fontello.ttf
PythonRengongzhinengZhongwenbanChuyi/font/fontello.woff
PythonRengongzhinengZhongwenbanChuyi/img/__init__.py
PythonRengongzhinengZhongwenbanChuyi/img/annotator-glyph-sprite.png
PythonRengongzhinengZhongwenbanChuyi/img/annotator-icon-sprite.png
PythonRengongzhinengZhongwenbanChuyi/img/apple-touch-icon.png
PythonRengongzhinengZhongwenbanChuyi/img/cancelfullscreen.png
PythonRengongzhinengZhongwenbanChuyi/img/close.png
PythonRengongzhinengZhongwenbanChuyi/img/fullscreen.png
PythonRengongzhinengZhongwenbanChuyi/img/loader.gif
PythonRengongzhinengZhongwenbanChuyi/img/menu-icon.png
PythonRengongzhinengZhongwenbanChuyi/img/save.png
PythonRengongzhinengZhongwenbanChuyi/img/saved.png
PythonRengongzhinengZhongwenbanChuyi/img/settings-s.png
PythonRengongzhinengZhongwenbanChuyi/img/settings.png
PythonRengongzhinengZhongwenbanChuyi/img/star.png
PythonRengongzhinengZhongwenbanChuyi/js/__init__.py
PythonRengongzhinengZhongwenbanChuyi/js/epub.js
PythonRengongzhinengZhongwenbanChuyi/js/epub.min.js
PythonRengongzhinengZhongwenbanChuyi/js/epub.min.map
PythonRengongzhinengZhongwenbanChuyi/js/hooks.min.js
PythonRengongzhinengZhongwenbanChuyi/js/hooks.min.map
PythonRengongzhinengZhongwenbanChuyi/js/reader.js
PythonRengongzhinengZhongwenbanChuyi/js/reader.js.map
python_rengongzhineng_zhongwenban_chuyi-2024.3.5.0.dist-info/METADATA
python_rengongzhineng_zhongwenban_chuyi-2024.3.5.0.dist-info/WHEEL
python_rengongzhineng_zhongwenban_chuyi-2024.3.5.0.dist-info/entry_points.txt
python_rengongzhineng_zhongwenban_chuyi-2024.3.5.0.dist-info/top_level.txt
python_rengongzhineng_zhongwenban_chuyi-2024.3.5.0.dist-info/RECORD
